{
  "githubRepo": "s2KawaiiVault",
  "githubToken": "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",
  "githubUserName": "PamNawi",
  "gardenBaseUrl": "",
  "prHistory": [],
  "baseTheme": "dark",
  "theme": "{\"name\":\"🔔 Chime\",\"author\":\"Ha'ani Whitlock\",\"repo\":\"Bluemoondragon07/chime-theme\",\"screenshot\":\"Chime.png\",\"modes\":[\"dark\",\"light\"],\"cssUrl\":\"https://raw.githubusercontent.com/Bluemoondragon07/chime-theme/HEAD/theme.css\"}",
  "faviconPath": "",
  "noteSettingsIsInitialized": true,
  "siteName": "Digital Garden",
  "slugifyEnabled": true,
  "noteIconKey": "dg-note-icon",
  "defaultNoteIcon": "",
  "showNoteIconOnTitle": false,
  "showNoteIconInFileTree": false,
  "showNoteIconOnInternalLink": false,
  "showNoteIconOnBackLink": false,
  "showCreatedTimestamp": true,
  "createdTimestampKey": "dg-created",
  "showUpdatedTimestamp": true,
  "updatedTimestampKey": "dg-updated",
  "timestampFormat": "MMM dd, yyyy h:mm a",
  "styleSettingsCss": "",
  "pathRewriteRules": "",
  "customFilters": [],
  "contentClassesKey": "dg-content-classes",
  "defaultNoteSettings": {
    "dgHomeLink": true,
    "dgPassFrontmatter": false,
    "dgShowBacklinks": false,
    "dgShowLocalGraph": false,
    "dgShowInlineTitle": false,
    "dgShowFileTree": false,
    "dgEnableSearch": false,
    "dgShowToc": false,
    "dgLinkPreview": false,
    "dgShowTags": false
  }
}